{
  "nodes": {
    "SitePage /dev-404-page/": {
      "layout": "index",
      "jsonName": "dev-404-page.json",
      "internalComponentName": "ComponentDev404Page",
      "path": "/dev-404-page/",
      "component": "/Users/Jimmy/Documents/jciclitira.com/portfolio-site/.cache/dev-404-page.js",
      "componentChunkName": "component---cache-dev-404-page-js",
      "context": {},
      "updatedAt": 1522346056157,
      "pluginCreator___NODE": "Plugin dev-404-page",
      "pluginCreatorId": "Plugin dev-404-page",
      "componentPath": "/Users/Jimmy/Documents/jciclitira.com/portfolio-site/.cache/dev-404-page.js",
      "id": "SitePage /dev-404-page/",
      "parent": "SOURCE",
      "children": [],
      "internal": {
        "type": "SitePage",
        "contentDigest": "23dd8eb112bf164de51a51252bad3088",
        "owner": "internal-data-bridge"
      }
    },
    "Plugin component-page-creator": {
      "resolve": "/Users/Jimmy/Documents/jciclitira.com/portfolio-site/node_modules/gatsby/dist/internal-plugins/component-page-creator",
      "id": "Plugin component-page-creator",
      "name": "component-page-creator",
      "version": "1.0.0",
      "pluginOptions": {
        "plugins": []
      },
      "nodeAPIs": [
        "createPagesStatefully"
      ],
      "pluginFilepath": "/Users/Jimmy/Documents/jciclitira.com/portfolio-site/node_modules/gatsby/dist/internal-plugins/component-page-creator",
      "packageJson": {
        "name": "component-page-creator",
        "description": "An internal Gatsby plugin that creates pages from component files in src/pages",
        "version": "1.0.0",
        "main": "index.js",
        "keywords": [
          "gatsby",
          "gatsby-plugin"
        ],
        "author": "Kyle Mathews <mathews.kyle@gmail.com>",
        "license": "MIT",
        "dependencies": [],
        "devDependencies": [],
        "peerDependencies": [],
        "optionalDependecies": [],
        "bundledDependecies": []
      },
      "parent": "SOURCE",
      "children": [],
      "internal": {
        "contentDigest": "e845af2762bd4303139f9457d79b92c1",
        "type": "SitePlugin",
        "owner": "internal-data-bridge"
      }
    },
    "Plugin component-layout-creator": {
      "resolve": "/Users/Jimmy/Documents/jciclitira.com/portfolio-site/node_modules/gatsby/dist/internal-plugins/component-layout-creator",
      "id": "Plugin component-layout-creator",
      "name": "component-layout-creator",
      "version": "1.0.0",
      "pluginOptions": {
        "plugins": []
      },
      "nodeAPIs": [
        "createLayouts"
      ],
      "pluginFilepath": "/Users/Jimmy/Documents/jciclitira.com/portfolio-site/node_modules/gatsby/dist/internal-plugins/component-layout-creator",
      "packageJson": {
        "name": "component-layout-creator",
        "description": "An internal Gatsby plugin that creates pages from component files in src/layouts",
        "version": "1.0.0",
        "main": "index.js",
        "keywords": [
          "gatsby",
          "gatsby-plugin"
        ],
        "author": "Kyle Mathews <mathews.kyle@gmail.com>",
        "license": "MIT",
        "dependencies": [],
        "devDependencies": [],
        "peerDependencies": [],
        "optionalDependecies": [],
        "bundledDependecies": []
      },
      "parent": "SOURCE",
      "children": [],
      "internal": {
        "contentDigest": "803b176008c3e8fbf24ca7e0204ce43b",
        "type": "SitePlugin",
        "owner": "internal-data-bridge"
      }
    },
    "Plugin internal-data-bridge": {
      "resolve": "/Users/Jimmy/Documents/jciclitira.com/portfolio-site/node_modules/gatsby/dist/internal-plugins/internal-data-bridge",
      "id": "Plugin internal-data-bridge",
      "name": "internal-data-bridge",
      "version": "1.0.0",
      "pluginOptions": {
        "plugins": []
      },
      "nodeAPIs": [
        "sourceNodes",
        "onCreatePage"
      ],
      "pluginFilepath": "/Users/Jimmy/Documents/jciclitira.com/portfolio-site/node_modules/gatsby/dist/internal-plugins/internal-data-bridge",
      "packageJson": {
        "name": "internal-data-bridge",
        "description": "An internal Gatsby plugin which creates data nodes from internal data",
        "version": "1.0.0",
        "main": "index.js",
        "author": "Kyle Mathews <mathews.kyle@gmail.com>",
        "license": "MIT",
        "dependencies": [],
        "devDependencies": [],
        "peerDependencies": [],
        "optionalDependecies": [],
        "bundledDependecies": []
      },
      "parent": "SOURCE",
      "children": [],
      "internal": {
        "contentDigest": "46b77c9214bff74c728930efb2bcc01c",
        "type": "SitePlugin",
        "owner": "internal-data-bridge"
      }
    },
    "Plugin dev-404-page": {
      "resolve": "/Users/Jimmy/Documents/jciclitira.com/portfolio-site/node_modules/gatsby/dist/internal-plugins/dev-404-page",
      "id": "Plugin dev-404-page",
      "name": "dev-404-page",
      "version": "1.0.0",
      "pluginOptions": {
        "plugins": []
      },
      "nodeAPIs": [
        "createPages"
      ],
      "pluginFilepath": "/Users/Jimmy/Documents/jciclitira.com/portfolio-site/node_modules/gatsby/dist/internal-plugins/dev-404-page",
      "packageJson": {
        "name": "dev-404-page",
        "description": "Internal plugin to add a 404 page in development with helpful information",
        "version": "1.0.0",
        "main": "index.js",
        "author": "Kyle Mathews <mathews.kyle@gmail.com>",
        "license": "MIT",
        "dependencies": [],
        "devDependencies": [],
        "peerDependencies": [],
        "optionalDependecies": [],
        "bundledDependecies": []
      },
      "parent": "SOURCE",
      "children": [],
      "internal": {
        "contentDigest": "c1a6a6f63f6ca56cdd424de9859117dc",
        "type": "SitePlugin",
        "owner": "internal-data-bridge"
      }
    },
    "Plugin prod-404": {
      "resolve": "/Users/Jimmy/Documents/jciclitira.com/portfolio-site/node_modules/gatsby/dist/internal-plugins/prod-404",
      "id": "Plugin prod-404",
      "name": "prod-404",
      "version": "1.0.0",
      "pluginOptions": {
        "plugins": []
      },
      "nodeAPIs": [
        "onCreatePage"
      ],
      "pluginFilepath": "/Users/Jimmy/Documents/jciclitira.com/portfolio-site/node_modules/gatsby/dist/internal-plugins/prod-404",
      "packageJson": {
        "name": "prod-404",
        "description": "Internal plugin to detect various flavors of 404 pages and ensure there's a 404.html path created as well to ensure compatability with static hosts",
        "version": "1.0.0",
        "main": "index.js",
        "author": "Kyle Mathews <mathews.kyle@gmail.com>",
        "license": "MIT",
        "dependencies": [],
        "devDependencies": [],
        "peerDependencies": [],
        "optionalDependecies": [],
        "bundledDependecies": []
      },
      "parent": "SOURCE",
      "children": [],
      "internal": {
        "contentDigest": "b523e4ff6031ee2d55ea9df6e1f28348",
        "type": "SitePlugin",
        "owner": "internal-data-bridge"
      }
    },
    "Plugin query-runner": {
      "resolve": "/Users/Jimmy/Documents/jciclitira.com/portfolio-site/node_modules/gatsby/dist/internal-plugins/query-runner",
      "id": "Plugin query-runner",
      "name": "query-runner",
      "version": "1.0.0",
      "pluginOptions": {
        "plugins": []
      },
      "nodeAPIs": [
        "onCreatePage",
        "onCreateLayout"
      ],
      "pluginFilepath": "/Users/Jimmy/Documents/jciclitira.com/portfolio-site/node_modules/gatsby/dist/internal-plugins/query-runner",
      "packageJson": {
        "name": "query-runner",
        "description": "Internal plugin for running queries",
        "version": "1.0.0",
        "main": "index.js",
        "author": "",
        "license": "MIT",
        "dependencies": [],
        "devDependencies": [],
        "peerDependencies": [],
        "optionalDependecies": [],
        "bundledDependecies": []
      },
      "parent": "SOURCE",
      "children": [],
      "internal": {
        "contentDigest": "8b3a728b1b88165b49a76579815aefaa",
        "type": "SitePlugin",
        "owner": "internal-data-bridge"
      }
    },
    "Plugin gatsby-plugin-react-helmet": {
      "resolve": "/Users/Jimmy/Documents/jciclitira.com/portfolio-site/node_modules/gatsby-plugin-react-helmet",
      "id": "Plugin gatsby-plugin-react-helmet",
      "name": "gatsby-plugin-react-helmet",
      "version": "2.0.3",
      "pluginOptions": {
        "plugins": []
      },
      "nodeAPIs": [],
      "pluginFilepath": "/Users/Jimmy/Documents/jciclitira.com/portfolio-site/node_modules/gatsby-plugin-react-helmet",
      "packageJson": {
        "name": "gatsby-plugin-react-helmet",
        "description": "Stub description for gatsby-plugin-react-helmet",
        "version": "2.0.3",
        "main": "index.js",
        "keywords": [
          "gatsby"
        ],
        "author": {
          "name": "Kyle Mathews &lt;mathews.kyle@gmail.com&gt;"
        },
        "license": "MIT",
        "dependencies": [
          {
            "name": "babel-runtime",
            "version": "^6.26.0"
          }
        ],
        "devDependencies": [
          {
            "name": "babel-cli",
            "version": "^6.26.0"
          },
          {
            "name": "cross-env",
            "version": "^5.0.5"
          }
        ],
        "peerDependencies": [
          {
            "name": "react-helmet",
            "version": ">=5.1.3"
          }
        ],
        "optionalDependecies": [],
        "bundledDependecies": []
      },
      "parent": "SOURCE",
      "children": [],
      "internal": {
        "contentDigest": "8f00a730e4b28444ee5185ad9fb277ca",
        "type": "SitePlugin",
        "owner": "internal-data-bridge"
      }
    },
    "Plugin default-site-plugin": {
      "resolve": "/Users/Jimmy/Documents/jciclitira.com/portfolio-site",
      "id": "Plugin default-site-plugin",
      "name": "default-site-plugin",
      "version": "eaa61ffe3f4a02839accddc7d0f7e9ce",
      "pluginOptions": {
        "plugins": []
      },
      "nodeAPIs": [],
      "pluginFilepath": "/Users/Jimmy/Documents/jciclitira.com/portfolio-site",
      "packageJson": {
        "name": "gatsby-starter-default",
        "version": "1.0.0",
        "main": "n/a",
        "keywords": [
          "gatsby"
        ],
        "author": "Kyle Mathews <mathews.kyle@gmail.com>",
        "license": "MIT",
        "dependencies": [
          {
            "name": "gatsby",
            "version": "^1.9.153"
          },
          {
            "name": "gatsby-link",
            "version": "^1.6.34"
          },
          {
            "name": "gatsby-plugin-react-helmet",
            "version": "^2.0.3"
          },
          {
            "name": "react-helmet",
            "version": "^5.2.0"
          }
        ],
        "devDependencies": [
          {
            "name": "prettier",
            "version": "^1.10.2"
          }
        ],
        "peerDependencies": [],
        "optionalDependecies": [],
        "bundledDependecies": []
      },
      "parent": "SOURCE",
      "children": [],
      "internal": {
        "contentDigest": "b7288c626f0042cc9009bdb8e3855f25",
        "type": "SitePlugin",
        "owner": "internal-data-bridge"
      }
    },
    "Site": {
      "siteMetadata": {
        "title": "Gatsby Default Starter"
      },
      "port": "8000",
      "host": "localhost",
      "pathPrefix": "",
      "polyfill": true,
      "buildTime": "2018-03-29T17:54:13.274Z",
      "id": "Site",
      "parent": "SOURCE",
      "children": [],
      "internal": {
        "contentDigest": "1455757e677abfefb42d637f085ebcf7",
        "type": "Site",
        "owner": "internal-data-bridge"
      }
    },
    "SitePage /404/": {
      "layout": "index",
      "jsonName": "404.json",
      "internalComponentName": "Component404",
      "path": "/404/",
      "component": "/Users/Jimmy/Documents/jciclitira.com/portfolio-site/src/pages/404.js",
      "componentChunkName": "component---src-pages-404-js",
      "context": {},
      "updatedAt": 1522346056182,
      "pluginCreator___NODE": "Plugin component-page-creator",
      "pluginCreatorId": "Plugin component-page-creator",
      "componentPath": "/Users/Jimmy/Documents/jciclitira.com/portfolio-site/src/pages/404.js",
      "id": "SitePage /404/",
      "parent": "SOURCE",
      "children": [],
      "internal": {
        "type": "SitePage",
        "contentDigest": "2d0911714acd8f998bdc4e5cfa175487",
        "owner": "internal-data-bridge"
      }
    },
    "SitePage /CrowdScores/": {
      "layout": "index",
      "jsonName": "crowd-scores.json",
      "internalComponentName": "ComponentCrowdScores",
      "path": "/CrowdScores/",
      "component": "/Users/Jimmy/Documents/jciclitira.com/portfolio-site/src/pages/CrowdScores.js",
      "componentChunkName": "component---src-pages-crowd-scores-js",
      "context": {},
      "updatedAt": 1522346056183,
      "pluginCreator___NODE": "Plugin component-page-creator",
      "pluginCreatorId": "Plugin component-page-creator",
      "componentPath": "/Users/Jimmy/Documents/jciclitira.com/portfolio-site/src/pages/CrowdScores.js",
      "id": "SitePage /CrowdScores/",
      "parent": "SOURCE",
      "children": [],
      "internal": {
        "type": "SitePage",
        "contentDigest": "db0b3e0dc749ea301b88ae39dffa6fc0",
        "owner": "internal-data-bridge"
      }
    },
    "SitePage /Gradient/": {
      "layout": "index",
      "jsonName": "gradient.json",
      "internalComponentName": "ComponentGradient",
      "path": "/Gradient/",
      "component": "/Users/Jimmy/Documents/jciclitira.com/portfolio-site/src/pages/Gradient.js",
      "componentChunkName": "component---src-pages-gradient-js",
      "context": {},
      "updatedAt": 1522346056183,
      "pluginCreator___NODE": "Plugin component-page-creator",
      "pluginCreatorId": "Plugin component-page-creator",
      "componentPath": "/Users/Jimmy/Documents/jciclitira.com/portfolio-site/src/pages/Gradient.js",
      "id": "SitePage /Gradient/",
      "parent": "SOURCE",
      "children": [],
      "internal": {
        "type": "SitePage",
        "contentDigest": "a306be5c87ada6d42d4326190fbf2913",
        "owner": "internal-data-bridge"
      }
    },
    "SitePage /Numilli/": {
      "layout": "index",
      "jsonName": "numilli.json",
      "internalComponentName": "ComponentNumilli",
      "path": "/Numilli/",
      "component": "/Users/Jimmy/Documents/jciclitira.com/portfolio-site/src/pages/Numilli.js",
      "componentChunkName": "component---src-pages-numilli-js",
      "context": {},
      "updatedAt": 1522346056184,
      "pluginCreator___NODE": "Plugin component-page-creator",
      "pluginCreatorId": "Plugin component-page-creator",
      "componentPath": "/Users/Jimmy/Documents/jciclitira.com/portfolio-site/src/pages/Numilli.js",
      "id": "SitePage /Numilli/",
      "parent": "SOURCE",
      "children": [],
      "internal": {
        "type": "SitePage",
        "contentDigest": "47b8c1627f087ba78a2ede1540ea343f",
        "owner": "internal-data-bridge"
      }
    },
    "SitePage /Quidco/": {
      "layout": "index",
      "jsonName": "quidco.json",
      "internalComponentName": "ComponentQuidco",
      "path": "/Quidco/",
      "component": "/Users/Jimmy/Documents/jciclitira.com/portfolio-site/src/pages/Quidco.js",
      "componentChunkName": "component---src-pages-quidco-js",
      "context": {},
      "updatedAt": 1522346056185,
      "pluginCreator___NODE": "Plugin component-page-creator",
      "pluginCreatorId": "Plugin component-page-creator",
      "componentPath": "/Users/Jimmy/Documents/jciclitira.com/portfolio-site/src/pages/Quidco.js",
      "id": "SitePage /Quidco/",
      "parent": "SOURCE",
      "children": [],
      "internal": {
        "type": "SitePage",
        "contentDigest": "747a4efa9d5c617ffc84220d9ed4c038",
        "owner": "internal-data-bridge"
      }
    },
    "SitePage /Suggestv/": {
      "layout": "index",
      "jsonName": "suggestv.json",
      "internalComponentName": "ComponentSuggestv",
      "path": "/Suggestv/",
      "component": "/Users/Jimmy/Documents/jciclitira.com/portfolio-site/src/pages/Suggestv.js",
      "componentChunkName": "component---src-pages-suggestv-js",
      "context": {},
      "updatedAt": 1522346056188,
      "pluginCreator___NODE": "Plugin component-page-creator",
      "pluginCreatorId": "Plugin component-page-creator",
      "componentPath": "/Users/Jimmy/Documents/jciclitira.com/portfolio-site/src/pages/Suggestv.js",
      "id": "SitePage /Suggestv/",
      "parent": "SOURCE",
      "children": [],
      "internal": {
        "type": "SitePage",
        "contentDigest": "7624719f4e026b7ef5258000f8c5f856",
        "owner": "internal-data-bridge"
      }
    },
    "SitePage /Thanks/": {
      "layout": "index",
      "jsonName": "thanks.json",
      "internalComponentName": "ComponentThanks",
      "path": "/Thanks/",
      "component": "/Users/Jimmy/Documents/jciclitira.com/portfolio-site/src/pages/Thanks.js",
      "componentChunkName": "component---src-pages-thanks-js",
      "context": {},
      "updatedAt": 1522346056189,
      "pluginCreator___NODE": "Plugin component-page-creator",
      "pluginCreatorId": "Plugin component-page-creator",
      "componentPath": "/Users/Jimmy/Documents/jciclitira.com/portfolio-site/src/pages/Thanks.js",
      "id": "SitePage /Thanks/",
      "parent": "SOURCE",
      "children": [],
      "internal": {
        "type": "SitePage",
        "contentDigest": "75f1db5dd508e53fbec8c3b5648dfd19",
        "owner": "internal-data-bridge"
      }
    },
    "SitePage /Weather/": {
      "layout": "index",
      "jsonName": "weather.json",
      "internalComponentName": "ComponentWeather",
      "path": "/Weather/",
      "component": "/Users/Jimmy/Documents/jciclitira.com/portfolio-site/src/pages/Weather.js",
      "componentChunkName": "component---src-pages-weather-js",
      "context": {},
      "updatedAt": 1522346056190,
      "pluginCreator___NODE": "Plugin component-page-creator",
      "pluginCreatorId": "Plugin component-page-creator",
      "componentPath": "/Users/Jimmy/Documents/jciclitira.com/portfolio-site/src/pages/Weather.js",
      "id": "SitePage /Weather/",
      "parent": "SOURCE",
      "children": [],
      "internal": {
        "type": "SitePage",
        "contentDigest": "6e793aacb6096fbdf57f94822b5961b8",
        "owner": "internal-data-bridge"
      }
    },
    "SitePage /Yunojuno/": {
      "layout": "index",
      "jsonName": "yunojuno.json",
      "internalComponentName": "ComponentYunojuno",
      "path": "/Yunojuno/",
      "component": "/Users/Jimmy/Documents/jciclitira.com/portfolio-site/src/pages/Yunojuno.js",
      "componentChunkName": "component---src-pages-yunojuno-js",
      "context": {},
      "updatedAt": 1522346056191,
      "pluginCreator___NODE": "Plugin component-page-creator",
      "pluginCreatorId": "Plugin component-page-creator",
      "componentPath": "/Users/Jimmy/Documents/jciclitira.com/portfolio-site/src/pages/Yunojuno.js",
      "id": "SitePage /Yunojuno/",
      "parent": "SOURCE",
      "children": [],
      "internal": {
        "type": "SitePage",
        "contentDigest": "64fc1e007e0b59c61e0e817743fc5d03",
        "owner": "internal-data-bridge"
      }
    },
    "SitePage /": {
      "layout": "index",
      "jsonName": "index.json",
      "internalComponentName": "ComponentIndex",
      "path": "/",
      "component": "/Users/Jimmy/Documents/jciclitira.com/portfolio-site/src/pages/index.js",
      "componentChunkName": "component---src-pages-index-js",
      "context": {},
      "updatedAt": 1522346056192,
      "pluginCreator___NODE": "Plugin component-page-creator",
      "pluginCreatorId": "Plugin component-page-creator",
      "componentPath": "/Users/Jimmy/Documents/jciclitira.com/portfolio-site/src/pages/index.js",
      "id": "SitePage /",
      "parent": "SOURCE",
      "children": [],
      "internal": {
        "type": "SitePage",
        "contentDigest": "23f7d2462a6b3fdefd8f7a155b594e81",
        "owner": "internal-data-bridge"
      }
    },
    "SitePage /page-2/": {
      "layout": "index",
      "jsonName": "page-2.json",
      "internalComponentName": "ComponentPage2",
      "path": "/page-2/",
      "component": "/Users/Jimmy/Documents/jciclitira.com/portfolio-site/src/pages/page-2.js",
      "componentChunkName": "component---src-pages-page-2-js",
      "context": {},
      "updatedAt": 1522346056193,
      "pluginCreator___NODE": "Plugin component-page-creator",
      "pluginCreatorId": "Plugin component-page-creator",
      "componentPath": "/Users/Jimmy/Documents/jciclitira.com/portfolio-site/src/pages/page-2.js",
      "id": "SitePage /page-2/",
      "parent": "SOURCE",
      "children": [],
      "internal": {
        "type": "SitePage",
        "contentDigest": "81f88ab6a61300e0fb0ecaf964c01826",
        "owner": "internal-data-bridge"
      }
    },
    "SitePage /404.html": {
      "layout": "index",
      "jsonName": "404-html.json",
      "internalComponentName": "Component404Html",
      "path": "/404.html",
      "component": "/Users/Jimmy/Documents/jciclitira.com/portfolio-site/src/pages/404.js",
      "componentChunkName": "component---src-pages-404-js",
      "context": {},
      "updatedAt": 1522346056208,
      "pluginCreator___NODE": "Plugin prod-404",
      "pluginCreatorId": "Plugin prod-404",
      "componentPath": "/Users/Jimmy/Documents/jciclitira.com/portfolio-site/src/pages/404.js",
      "id": "SitePage /404.html",
      "parent": "SOURCE",
      "children": [],
      "internal": {
        "type": "SitePage",
        "contentDigest": "a6afe4ee2b3fb12b62d0896649a76720",
        "owner": "internal-data-bridge"
      }
    }
  },
  "status": {
    "plugins": {},
    "PLUGINS_HASH": "d537cba632046ea7bf0197069ffe1294"
  },
  "componentDataDependencies": {
    "nodes": {},
    "connections": {
      "SitePage": [
        "/dev-404-page/"
      ]
    }
  }
}